driftradar_vision/__about__.py
driftradar_vision/__init__.py
driftradar_vision/artifacts.py
driftradar_vision/backtest.py
driftradar_vision/corruptions.py
driftradar_vision/data_prod.py
driftradar_vision/data_ref.py
driftradar_vision/dq_validate.py
driftradar_vision/drift_check.py
driftradar_vision/embeddings.py
driftradar_vision/eval.py
driftradar_vision/features.py
driftradar_vision/logging.py
driftradar_vision/metrics.py
driftradar_vision/models.py
driftradar_vision/predict.py
driftradar_vision/prediction_drift.py
driftradar_vision/registry.py
driftradar_vision/retrain.py
driftradar_vision/train.py
driftradar_vision/viz.py
driftradar_vision/utils/hashing.py
driftradar_vision/utils/io.py
driftradar_vision/utils/paths.py
driftradar_vision/utils/seeds.py
driftradar_vision/utils/timer.py
driftradar_vision-0.1.0.dist-info/licenses/LICENSE
driftradar_vision-0.1.0.dist-info/METADATA
driftradar_vision-0.1.0.dist-info/WHEEL
driftradar_vision-0.1.0.dist-info/top_level.txt
driftradar_vision-0.1.0.dist-info/RECORD
