Metadata-Version: 2.4
Name: driftradar-vision
Version: 0.1.0
Summary: Vision drift monitoring with Great Expectations + Evidently + MLflow (Milestone A: DQ gates).
Author-email: Abdulvahap Mutlu <abdulvahapmutlu1@gmail.com>
License: MIT
Classifier: Programming Language :: Python :: 3
Classifier: License :: OSI Approved :: MIT License
Requires-Python: >=3.11
License-File: LICENSE
Requires-Dist: torch>=2.3
Requires-Dist: torchvision>=0.18
Requires-Dist: numpy>=1.26
Requires-Dist: pandas>=2.2
Requires-Dist: pillow>=10.3
Requires-Dist: opencv-python>=4.9
Requires-Dist: albumentations>=1.4
Requires-Dist: scikit-learn>=1.4
Requires-Dist: hydra-core>=1.3
Requires-Dist: omegaconf>=2.3
Requires-Dist: rich>=13.7
Requires-Dist: structlog>=24.1
Requires-Dist: tqdm>=4.66
Requires-Dist: mlflow>=2.14
Requires-Dist: evidently>=0.5.0
Requires-Dist: great-expectations>=0.18
Requires-Dist: jinja2>=3.1
Requires-Dist: pyarrow>=15.0
Requires-Dist: polars>=1.6
Requires-Dist: matplotlib>=3.8
Requires-Dist: plotly>=5.22
Provides-Extra: dev
Requires-Dist: pytest>=8.0; extra == "dev"
Requires-Dist: pytest-cov>=5.0; extra == "dev"
Requires-Dist: pytest-sugar>=1.0; extra == "dev"
Requires-Dist: ruff>=0.6.9; extra == "dev"
Requires-Dist: black>=24.8; extra == "dev"
Requires-Dist: mypy>=1.11; extra == "dev"
Requires-Dist: types-PyYAML>=6.0.12; extra == "dev"
Requires-Dist: ipykernel; extra == "dev"
Requires-Dist: pre-commit; extra == "dev"
Dynamic: license-file
